Design/IIR_Biquad_Notch_Filter/IIR.v
////////////////////////////////////////////////////////////////////////////////
// Author: Amira Atef
// Design: 2nd Order Infinite Impulse Response Notch Filter
// Date: 11-11-2025
// Description: An IIR module configurable for 1MHz (5MHz) and 2.4MHz coefficients 
// implemented using transposed Direct Form II. 
////////////////////////////////////////////////////////////////////////////////

module IIR #(parameter DATA_WIDTH = 16)(
    input wire clk, // 18MHz, to avoid CDC
    input wire rst_n,
    input wire [1:0] f_c, // Centre Frequency 0 (1MHz) or 1 (2.4MHz) or 2 (2MHz)
    input wire signed [DATA_WIDTH-1:0] x_in,
    output reg signed [DATA_WIDTH-1:0] x_out
);
    localparam signed [DATA_WIDTH-1:0] b0_0 = 16'h4609;
    localparam signed [DATA_WIDTH-1:0] b0_1 = 16'hB9F7;
    localparam signed [DATA_WIDTH-1:0] b0_2 = 16'h4609;
    localparam signed [DATA_WIDTH-1:0] b1_0 = 16'h2360;
    localparam signed [DATA_WIDTH-1:0] b1_1 = 16'h393C;
    localparam signed [DATA_WIDTH-1:0] b1_2 = 16'h2360;
    localparam signed [DATA_WIDTH-1:0] b2_0 = 16'h4609;
    localparam signed [DATA_WIDTH-1:0] b2_1 = 16'h4609;
    localparam signed [DATA_WIDTH-1:0] b2_2 = 16'h4609;

    localparam signed [DATA_WIDTH-1:0] a0_1 = 16'hB9F7;
    localparam signed [DATA_WIDTH-1:0] a0_2 = 16'h0C12;
    localparam signed [DATA_WIDTH-1:0] a1_1 = 16'h393C;
    localparam signed [DATA_WIDTH-1:0] a1_2 = 16'hC6C0;
    localparam signed [DATA_WIDTH-1:0] a2_1 = 16'h4609;
    localparam signed [DATA_WIDTH-1:0] a2_2 = 16'h0C12;

    reg signed [DATA_WIDTH-1:0] b0, b1, b2;
    reg signed [DATA_WIDTH-1:0] a1, a2;

    reg signed [(DATA_WIDTH<<1)-1:0] stagef0, stagef1, stagef2; // forward
    reg signed [(DATA_WIDTH<<1)-1:0] stageb1, stageb2; // backward

    reg signed [DATA_WIDTH<<1:0] delay2_1, delay2_2, delay1_1, delay1_2;

    reg [1:0] count;

    always @(*) begin
        case (f_c)
            2'd0: begin
                b0 = b0_0;
                b1 = b0_1;
                b2 = b0_2;
                a1 = a0_1;
                a2 = a0_2;
            end
            2'd1: begin
                b0 = b1_0;
                b1 = b1_1;
                b2 = b1_2;
                a1 = a1_1;
                a2 = a1_2;
            end 
            2'd2: begin
                b0 = b2_0;
                b1 = b2_1;
                b2 = b2_2;
                a1 = a2_1;
                a2 = a2_2;
            end 
            default: begin
                b0 = 'b0;
                b1 = 'b0;
                b2 = 'b0;
                a1 = 'b0;
                a2 = 'b0;
            end
        endcase
    end

    always @(posedge clk or negedge rst_n) begin
        if (!rst_n) begin
            x_out    <= 'd0;
            stagef0  <= 'd0;
            stagef1  <= 'd0;
            stagef2  <= 'd0; 
            stageb1  <= 'd0;
            stageb2  <= 'd0;
            delay2_1 <= 'd0;
            delay2_2 <= 'd0;
            delay1_1 <= 'd0;
            delay1_2 <= 'd0;
            count <= 2'b0;
        end
        else if (count[1]) begin // for 6MHz
            count <= 2'b0;
            stagef0 <= x_in * b0;
            stagef1 <= x_in * b1;
            stagef2 <= x_in * b2; 
            stageb1 <= (delay1_2 + stagef0) * a1;
            stageb2 <= (delay1_2 + stagef0) * a2;
            
            delay2_1 <= stagef2 + stageb2;
            delay2_2 <= delay2_1;

            delay1_1 <= delay2_2 + stagef1 + stageb1;
            delay1_2 <= delay1_1;

            // x_out <= (delay1_2 + stagef0) >>> DATA_WIDTH;
            x_out <= ((delay1_2 + stagef0) + (1<<(DATA_WIDTH-2))) >> (DATA_WIDTH-1);

        end else
            count <= count + 1;
    end
endmodule

Design/IIR_Biquad_Notch_Filter/Cascaded_IIR.v
module Cascaded_IIR #(parameter DATA_WIDTH = 16)(
    input wire clk, // 18MHz, to avoid CDC
    input wire rst_n,
    input wire signed [DATA_WIDTH-1:0] x_in,
    output wire signed [DATA_WIDTH-1:0] x_out
);

wire signed [DATA_WIDTH-1:0] out_1, out_2;

IIR #(.DATA_WIDTH(DATA_WIDTH)) IIR_2_4 (
    .clk(clk), // 18MHz, to avoid CDC
    .rst_n(rst_n),
    .f_c(2'b1), // Centre Frequency 0 (1MHz) or 1 (2.4MHz) or 2 (2MHz)
    .x_in(x_in),
    .x_out(out_1)
);

IIR #(.DATA_WIDTH(DATA_WIDTH)) IIR_1 (
    .clk(clk), // 18MHz, to avoid CDC
    .rst_n(rst_n),
    .f_c(2'b0), // Centre Frequency 0 (1MHz) or 1 (2.4MHz) or 2 (2MHz)
    .x_in(out_1),
    .x_out(out_2)
);

IIR #(.DATA_WIDTH(DATA_WIDTH)) IIR_2 (
    .clk(clk), // 18MHz, to avoid CDC
    .rst_n(rst_n),
    .f_c(2'b10), // Centre Frequency 0 (1MHz) or 1 (2.4MHz) or 2 (2MHz)
    .x_in(out_2),
    .x_out(x_out)
);

endmodule

Design/IIR_Biquad_Notch_Filter/Cascaded_IIR_tb.v
`timescale 1ns/1fs
module Cascaded_IIR_tb();

    /////////////////////////////////////////////////////////
    ///////////////////// Parameters ////////////////////////
    /////////////////////////////////////////////////////////

    parameter CLOCK_PERIOD = 55.555556;
    parameter CLOCK_PERIOD_6 = CLOCK_PERIOD * 3;
    parameter DATA_WIDTH = 16;
    parameter DATA_DEPTH = 667;

    /////////////////////////////////////////////////////////
    /////////// Testbench Signal Declaration ////////////////
    /////////////////////////////////////////////////////////

    reg clk_6;
    reg clk_tb, rst_n_tb;
    reg signed [DATA_WIDTH-1:0] x_in_tb; // s16.15 format
    wire signed [DATA_WIDTH-1:0] x_out_tb; // s16.15 format
    reg signed [DATA_WIDTH-1:0] x_out_expec; // s16.15 format
    // reg signed [DATA_WIDTH-1:0] coeff;

    reg signed [DATA_WIDTH-1:0] mem_in [0:DATA_DEPTH-1]; // memory to store input samples
    reg signed [DATA_WIDTH-1:0] mem_out [0:DATA_DEPTH-1]; // memory to store output samples
    // reg signed [DATA_WIDTH-1:0] mem_coeff [0:17]; 

    integer i;

    ////////////////////////////////////////////////////////
    /////////////////// DUT Instantation ///////////////////
    ////////////////////////////////////////////////////////

    Cascaded_IIR #(.DATA_WIDTH(DATA_WIDTH)) DUT (.clk(clk_tb), .rst_n(rst_n_tb), .x_in(x_in_tb), .x_out(x_out_tb));

    ////////////////////////////////////////////////////////
    ////////////////// Clock Generator  ////////////////////
    ////////////////////////////////////////////////////////

    always #(CLOCK_PERIOD/2) clk_tb = ~clk_tb;
    always #(CLOCK_PERIOD_6/2) clk_6 = ~clk_6;

    ////////////////////////////////////////////////////////
    /////////// Applying Stimulus on Inputs //////////////// 
    ////////////////////////////////////////////////////////

    initial begin
        // System Functions
        $dumpfile("IIR.vcd");
        $dumpvars;
        // Load input samples from file
        $readmemh("inputs_IIR.txt", mem_in);
        $readmemh("outputs_IIR.txt", mem_out);
        // $readmemb("coeff.txt", mem_coeff);

        // initialization
        initialize();
        
        // for (i = 0; i < 18; i = i + 1) begin
        //     coeff = mem_coeff[i];
        //     #(CLOCK_PERIOD_6); // for 6MHz input rate
        // end

        for (i = 0; i < DATA_DEPTH; i = i + 1) begin
            x_in_tb = mem_in[i];
            x_out_expec = mem_out[i];
            #(CLOCK_PERIOD_6); // for 6MHz input rate
        end

        #(500*CLOCK_PERIOD)
        $stop;
    end

    ////////////////////////////////////////////////////////
    /////////////////////// TASKS //////////////////////////
    ////////////////////////////////////////////////////////

    /////////////// Signals Initialization //////////////////

    task initialize;
        begin
            clk_tb  	  = 1'b0;
            clk_6         = 1'b0;
            // x_in_tb       = 16'sd16384; // 0.5 in s16.15 format
            reset();
        end	
    endtask

    ///////////////////////// RESET /////////////////////////

    task reset;
        begin
            rst_n_tb = 1'b1;
            #(CLOCK_PERIOD)
            rst_n_tb = 1'b0;
            #(CLOCK_PERIOD)
            rst_n_tb = 1'b1;
        end
    endtask

    ////////////////// Check Out Response  ////////////////////

endmodule

Design/IIR_Biquad_Notch_Filter/IIR.vcd
$date
	Thu Nov 13 00:10:14 2025
$end
$version
	QuestaSim Version 2021.1
$end
$timescale
	1fs
$end

$scope module Cascaded_IIR_tb $end
$var parameter 0 ! CLOCK_PERIOD $end
$var parameter 0 " CLOCK_PERIOD_6 $end
$var parameter 32 # DATA_WIDTH $end
$var parameter 32 $ DATA_DEPTH $end
$var reg 1 % clk_6 $end
$var reg 1 & clk_tb $end
$var reg 1 ' rst_n_tb $end
$var reg 16 ( x_in_tb [15:0] $end
$var wire 1 ) x_out_tb [15] $end
$var wire 1 * x_out_tb [14] $end
$var wire 1 + x_out_tb [13] $end
$var wire 1 , x_out_tb [12] $end
$var wire 1 - x_out_tb [11] $end
$var wire 1 . x_out_tb [10] $end
$var wire 1 / x_out_tb [9] $end
$var wire 1 0 x_out_tb [8] $end
$var wire 1 1 x_out_tb [7] $end
$var wire 1 2 x_out_tb [6] $end
$var wire 1 3 x_out_tb [5] $end
$var wire 1 4 x_out_tb [4] $end
$var wire 1 5 x_out_tb [3] $end
$var wire 1 6 x_out_tb [2] $end
$var wire 1 7 x_out_tb [1] $end
$var wire 1 8 x_out_tb [0] $end
$var reg 16 9 x_out_expec [15:0] $end
$var integer 32 : i $end

$scope task initialize $end
$upscope $end

$scope task reset $end
$upscope $end

$scope module DUT $end
$var parameter 32 ; DATA_WIDTH $end
$var wire 1 < clk $end
$var wire 1 = rst_n $end
$var wire 1 > x_in [15] $end
$var wire 1 ? x_in [14] $end
$var wire 1 @ x_in [13] $end
$var wire 1 A x_in [12] $end
$var wire 1 B x_in [11] $end
$var wire 1 C x_in [10] $end
$var wire 1 D x_in [9] $end
$var wire 1 E x_in [8] $end
$var wire 1 F x_in [7] $end
$var wire 1 G x_in [6] $end
$var wire 1 H x_in [5] $end
$var wire 1 I x_in [4] $end
$var wire 1 J x_in [3] $end
$var wire 1 K x_in [2] $end
$var wire 1 L x_in [1] $end
$var wire 1 M x_in [0] $end
$var wire 1 ) x_out [15] $end
$var wire 1 * x_out [14] $end
$var wire 1 + x_out [13] $end
$var wire 1 , x_out [12] $end
$var wire 1 - x_out [11] $end
$var wire 1 . x_out [10] $end
$var wire 1 / x_out [9] $end
$var wire 1 0 x_out [8] $end
$var wire 1 1 x_out [7] $end
$var wire 1 2 x_out [6] $end
$var wire 1 3 x_out [5] $end
$var wire 1 4 x_out [4] $end
$var wire 1 5 x_out [3] $end
$var wire 1 6 x_out [2] $end
$var wire 1 7 x_out [1] $end
$var wire 1 8 x_out [0] $end
$var wire 1 N out_1 [15] $end
$var wire 1 O out_1 [14] $end
$var wire 1 P out_1 [13] $end
$var wire 1 Q out_1 [12] $end
$var wire 1 R out_1 [11] $end
$var wire 1 S out_1 [10] $end
$var wire 1 T out_1 [9] $end
$var wire 1 U out_1 [8] $end
$var wire 1 V out_1 [7] $end
$var wire 1 W out_1 [6] $end
$var wire 1 X out_1 [5] $end
$var wire 1 Y out_1 [4] $end
$var wire 1 Z out_1 [3] $end
$var wire 1 [ out_1 [2] $end
$var wire 1 \ out_1 [1] $end
$var wire 1 ] out_1 [0] $end
$var wire 1 ^ out_2 [15] $end
$var wire 1 _ out_2 [14] $end
$var wire 1 ` out_2 [13] $end
$var wire 1 a out_2 [12] $end
$var wire 1 b out_2 [11] $end
$var wire 1 c out_2 [10] $end
$var wire 1 d out_2 [9] $end
$var wire 1 e out_2 [8] $end
$var wire 1 f out_2 [7] $end
$var wire 1 g out_2 [6] $end
$var wire 1 h out_2 [5] $end
$var wire 1 i out_2 [4] $end
$var wire 1 j out_2 [3] $end
$var wire 1 k out_2 [2] $end
$var wire 1 l out_2 [1] $end
$var wire 1 m out_2 [0] $end

$scope module IIR_2_4 $end
$var parameter 32 n DATA_WIDTH $end
$var parameter 16 o b0_0 $end
$var parameter 16 p b0_1 $end
$var parameter 16 q b0_2 $end
$var parameter 16 r b1_0 $end
$var parameter 16 s b1_1 $end
$var parameter 16 t b1_2 $end
$var parameter 16 u b2_0 $end
$var parameter 16 v b2_1 $end
$var parameter 16 w b2_2 $end
$var parameter 16 x a0_1 $end
$var parameter 16 y a0_2 $end
$var parameter 16 z a1_1 $end
$var parameter 16 { a1_2 $end
$var parameter 16 | a2_1 $end
$var parameter 16 } a2_2 $end
$var wire 1 < clk $end
$var wire 1 = rst_n $end
$var wire 1 ~ f_c [1] $end
$var wire 1 !! f_c [0] $end
$var wire 1 > x_in [15] $end
$var wire 1 ? x_in [14] $end
$var wire 1 @ x_in [13] $end
$var wire 1 A x_in [12] $end
$var wire 1 B x_in [11] $end
$var wire 1 C x_in [10] $end
$var wire 1 D x_in [9] $end
$var wire 1 E x_in [8] $end
$var wire 1 F x_in [7] $end
$var wire 1 G x_in [6] $end
$var wire 1 H x_in [5] $end
$var wire 1 I x_in [4] $end
$var wire 1 J x_in [3] $end
$var wire 1 K x_in [2] $end
$var wire 1 L x_in [1] $end
$var wire 1 M x_in [0] $end
$var reg 16 "! x_out [15:0] $end
$var reg 16 #! b0 [15:0] $end
$var reg 16 $! b1 [15:0] $end
$var reg 16 %! b2 [15:0] $end
$var reg 16 &! a1 [15:0] $end
$var reg 16 '! a2 [15:0] $end
$var reg 32 (! stagef0 [31:0] $end
$var reg 32 )! stagef1 [31:0] $end
$var reg 32 *! stagef2 [31:0] $end
$var reg 32 +! stageb1 [31:0] $end
$var reg 32 ,! stageb2 [31:0] $end
$var reg 33 -! delay2_1 [32:0] $end
$var reg 33 .! delay2_2 [32:0] $end
$var reg 33 /! delay1_1 [32:0] $end
$var reg 33 0! delay1_2 [32:0] $end
$var reg 2 1! count [1:0] $end
$upscope $end

$scope module IIR_1 $end
$var parameter 32 2! DATA_WIDTH $end
$var parameter 16 3! b0_0 $end
$var parameter 16 4! b0_1 $end
$var parameter 16 5! b0_2 $end
$var parameter 16 6! b1_0 $end
$var parameter 16 7! b1_1 $end
$var parameter 16 8! b1_2 $end
$var parameter 16 9! b2_0 $end
$var parameter 16 :! b2_1 $end
$var parameter 16 ;! b2_2 $end
$var parameter 16 <! a0_1 $end
$var parameter 16 =! a0_2 $end
$var parameter 16 >! a1_1 $end
$var parameter 16 ?! a1_2 $end
$var parameter 16 @! a2_1 $end
$var parameter 16 A! a2_2 $end
$var wire 1 < clk $end
$var wire 1 = rst_n $end
$var wire 1 B! f_c [1] $end
$var wire 1 C! f_c [0] $end
$var wire 1 N x_in [15] $end
$var wire 1 O x_in [14] $end
$var wire 1 P x_in [13] $end
$var wire 1 Q x_in [12] $end
$var wire 1 R x_in [11] $end
$var wire 1 S x_in [10] $end
$var wire 1 T x_in [9] $end
$var wire 1 U x_in [8] $end
$var wire 1 V x_in [7] $end
$var wire 1 W x_in [6] $end
$var wire 1 X x_in [5] $end
$var wire 1 Y x_in [4] $end
$var wire 1 Z x_in [3] $end
$var wire 1 [ x_in [2] $end
$var wire 1 \ x_in [1] $end
$var wire 1 ] x_in [0] $end
$var reg 16 D! x_out [15:0] $end
$var reg 16 E! b0 [15:0] $end
$var reg 16 F! b1 [15:0] $end
$var reg 16 G! b2 [15:0] $end
$var reg 16 H! a1 [15:0] $end
$var reg 16 I! a2 [15:0] $end
$var reg 32 J! stagef0 [31:0] $end
$var reg 32 K! stagef1 [31:0] $end
$var reg 32 L! stagef2 [31:0] $end
$var reg 32 M! stageb1 [31:0] $end
$var reg 32 N! stageb2 [31:0] $end
$var reg 33 O! delay2_1 [32:0] $end
$var reg 33 P! delay2_2 [32:0] $end
$var reg 33 Q! delay1_1 [32:0] $end
$var reg 33 R! delay1_2 [32:0] $end
$var reg 2 S! count [1:0] $end
$upscope $end

$scope module IIR_2 $end
$var parameter 32 T! DATA_WIDTH $end
$var parameter 16 U! b0_0 $end
$var parameter 16 V! b0_1 $end
$var parameter 16 W! b0_2 $end
$var parameter 16 X! b1_0 $end
$var parameter 16 Y! b1_1 $end
$var parameter 16 Z! b1_2 $end
$var parameter 16 [! b2_0 $end
$var parameter 16 \! b2_1 $end
$var parameter 16 ]! b2_2 $end
$var parameter 16 ^! a0_1 $end
$var parameter 16 _! a0_2 $end
$var parameter 16 `! a1_1 $end
$var parameter 16 a! a1_2 $end
$var parameter 16 b! a2_1 $end
$var parameter 16 c! a2_2 $end
$var wire 1 < clk $end
$var wire 1 = rst_n $end
$var wire 1 d! f_c [1] $end
$var wire 1 e! f_c [0] $end
$var wire 1 ^ x_in [15] $end
$var wire 1 _ x_in [14] $end
$var wire 1 ` x_in [13] $end
$var wire 1 a x_in [12] $end
$var wire 1 b x_in [11] $end
$var wire 1 c x_in [10] $end
$var wire 1 d x_in [9] $end
$var wire 1 e x_in [8] $end
$var wire 1 f x_in [7] $end
$var wire 1 g x_in [6] $end
$var wire 1 h x_in [5] $end
$var wire 1 i x_in [4] $end
$var wire 1 j x_in [3] $end
$var wire 1 k x_in [2] $end
$var wire 1 l x_in [1] $end
$var wire 1 m x_in [0] $end
$var reg 16 f! x_out [15:0] $end
$var reg 16 g! b0 [15:0] $end
$var reg 16 h! b1 [15:0] $end
$var reg 16 i! b2 [15:0] $end
$var reg 16 j! a1 [15:0] $end
$var reg 16 k! a2 [15:0] $end
$var reg 32 l! stagef0 [31:0] $end
$var reg 32 m! stagef1 [31:0] $end
$var reg 32 n! stagef2 [31:0] $end
$var reg 32 o! stageb1 [31:0] $end
$var reg 32 p! stageb2 [31:0] $end
$var reg 33 q! delay2_1 [32:0] $end
$var reg 33 r! delay2_2 [32:0] $end
$var reg 33 s! delay1_1 [32:0] $end
$var reg 33 t! delay1_2 [32:0] $end
$var reg 2 u! count [1:0] $end
$upscope $end
$upscope $end
$upscope $end
$enddefinitions $end
#0
$dumpvars
0%
0&
1'
bx (
bx 9
bx "!
b10001101100000 #!
b11100100111100 $!
b10001101100000 %!
b11100100111100 &!
b1100011011000000 '!
bx (!
bx )!
bx *!
bx +!
bx ,!
bx -!
bx .!
bx /!
bx 0!
bx 1!
bx D!
b100011000001001 E!
b1011100111110111 F!
b100011000001001 G!
b1011100111110111 H!
b110000010010 I!
bx J!
bx K!
bx L!
bx M!
bx N!
bx O!
bx P!
bx Q!
bx R!
bx S!
bx f!
b100011000001001 g!
b100011000001001 h!
b100011000001001 i!
b100011000001001 j!
b110000010010 k!
bx l!
bx m!
bx n!
bx o!
bx p!
bx q!
bx r!
bx s!
bx t!
bx u!
b10000 #
b1010011011 $
b10000 ;
b10000 n
b100011000001001 o
b1011100111110111 p
b100011000001001 q
b10001101100000 r
b11100100111100 s
b10001101100000 t
b100011000001001 u
b100011000001001 v
b100011000001001 w
b1011100111110111 x
b110000010010 y
b11100100111100 z
b1100011011000000 {
b100011000001001 |
b110000010010 }
b10000 2!
b100011000001001 3!
b1011100111110111 4!
b100011000001001 5!
b10001101100000 6!
b11100100111100 7!
b10001101100000 8!
b100011000001001 9!
b100011000001001 :!
b100011000001001 ;!
b1011100111110111 <!
b110000010010 =!
b11100100111100 >!
b1100011011000000 ?!
b100011000001001 @!
b110000010010 A!
b10000 T!
b100011000001001 U!
b1011100111110111 V!
b100011000001001 W!
b10001101100000 X!
b11100100111100 Y!
b10001101100000 Z!
b100011000001001 [!
b100011000001001 \!
b100011000001001 ]!
b1011100111110111 ^!
b110000010010 _!
b11100100111100 `!
b1100011011000000 a!
b100011000001001 b!
b110000010010 c!
r55.555556 !
r166.666668 "
bx :
x8
x7
x6
x5
x4
x3
x2
x1
x0
x/
x.
x-
x,
x+
x*
x)
x]
x\
x[
xZ
xY
xX
xW
xV
xU
xT
xS
xR
xQ
xP
xO
xN
xm
xl
xk
xj
xi
xh
xg
xf
xe
xd
xc
xb
xa
x`
x_
x^
xM
xL
xK
xJ
xI
xH
xG
xF
xE
xD
xC
xB
xA
x@
x?
x>
1=
0<
0e!
1d!
0C!
0B!
1!!
0~
$end
#27777778
1&
1<
#55555556
0'
0&
0=
0<
b0 "!
b0 -!
b0 /!
b0 1!
b0 D!
b0 O!
b0 Q!
b0 S!
b0 f!
b0 q!
b0 s!
b0 u!
08
07
06
05
04
03
02
01
00
0/
0.
0-
0,
0+
0*
0)
0m
0l
0k
0j
0i
0h
0g
0f
0e
0d
0c
0b
0a
0`
0_
0^
0]
0\
0[
0Z
0Y
0X
0W
0V
0U
0T
0S
0R
0Q
0P
0O
0N
b0 l!
b0 m!
b0 n!
b0 o!
b0 p!
b0 J!
b0 K!
b0 L!
b0 M!
b0 N!
#83333334
1%
1&
1<
#111111112
1'
b0 :
b0 (
b0 9
0&
1=
0M
0L
0K
0J
0I
0H
0G
0F
0E
0D
0C
0B
0A
0@
0?
0>
0<
b0 (!
b0 )!
b0 *!
b0 +!
b0 ,!
#138888890
1&
1<
b1 1!
b1 S!
b1 u!
#166666668
0%
0&
0<
#194444446
1&
1<
b10 u!
b10 S!
b10 1!
#222222224
0&
0<
#250000002
1%
1&
1<
b0 1!
bx /!
b0 S!
bx Q!
b0 u!
bx s!
bx o!
bx p!
bx M!
bx N!
bx +!
bx ,!
#277777780
b1 :
b1111111111110010 (
b1111111111111111 9
0&
1L
1I
1H
1G
1F
1E
1D
1C
1B
1A
1@
1?
1>
0<
b11111111111111100001000011000000 (!
b11111111111111001101111010111000 )!
b11111111111111100001000011000000 *!
#305555558
1&
1<
b1 u!
b1 S!
b1 1!
#333333336
0%
0&
0<
#361111114
1&
1<
b10 1!
b10 S!
b10 u!
#388888892
0&
0<
#416666670
1%
1&
1<
b0 u!
bx q!
bx f!
b0 S!
bx O!
bx D!
b0 1!
bx -!
bx "!
x8
x7
x6
x5
x4
x3
x2
x1
x0
x/
x.
x-
x,
x+
x*
x)
x]
x\
x[
xZ
xY
xX
xW
xV
xU
xT
xS
xR
xQ
xP
xO
xN
xm
xl
xk
xj
xi
xh
xg
xf
xe
xd
xc
xb
xa
x`
x_
x^
bx l!
bx m!
bx n!
bx J!
bx K!
bx L!
#444444448
b10 :
b1111111111101110 (
b1111111111111101 9
0&
1K
1J
0I
0<
b11111111111111011000001101000000 (!
b11111111111110111111100111001000 )!
b11111111111111011000001101000000 *!
#472222226
1&
1<
b1 1!
b1 S!
b1 u!
#500000004
0%
0&
0<
#527777782
1&
1<
b10 u!
b10 S!
b10 1!
#555555560
0&
0<
#583333338
1%
1&
1<
b0 1!
b0 S!
b0 u!
#611111116
b11 :
b1111111111010010 (
b1111111111111000 9
0&
0K
0J
1I
0H
0<
b11111111111110011010010011000000 (!
b11111111111101011011011100111000 )!
b11111111111110011010010011000000 *!
#638888894
1&
1<
b1 u!
b1 S!
b1 1!
#666666672
0%
0&
0<
#694444450
1&
1<
b10 1!
b10 S!
b10 u!
#722222228
0&
0<
#750000006
1%
1&
1<
b0 u!
b0 S!
b0 1!
#777777784
b100 :
b1000001 (
b1111111111111100 9
0&
1M
0L
0I
0F
0E
0D
0C
0B
0A
0@
0?
0>
0<
b10001111101101100000 (!
b11101000100000111100 )!
b10001111101101100000 *!
#805555562
1&
1<
b1 1!
b1 S!
b1 u!
#833333340
0%
0&
0<
#861111118
1&
1<
b10 u!
b10 S!
b10 1!
#888888896
0&
0<
#916666674
1%
1&
1<
b0 1!
b0 S!
b0 u!
#944444452
b101 :
b1101100 (
b10 9
0&
0M
1K
1J
1H
0<
b11101110110010000000 (!
b110000010010101010000 )!
b11101110110010000000 *!
#972222230
1&
1<
b1 u!
b1 S!
b1 1!
#1000000008
0%
0&
0<
#1027777786
1&
1<
b10 1!
b10 S!
b10 u!
#1055555564
0&
0<
#1083333342
1%
1&
1<
b0 u!
b0 S!
b0 1!
#1111111120
b110 :
b100010 (
b1101 9
0&
1L
0K
0J
0G
0<
b1001011001011000000 (!
b1111001100111111000 )!
b1001011001011000000 *!
#1138888898
1&
1<
b1 1!
b1 S!
b1 u!
#1166666676
0%
0&
0<
#1194444454
1&
1<
b10 u!
b10 S!
b10 1!
#1222222232
0&
0<
#1250000010
1%
1&
1<
b0 1!
b0 S!
b0 u!
#1277777788
b111 :
b10010100 (
b11100 9
0&
0L
1K
1I
0H
1F
0<
b101000111001110000000 (!
b1000010001011010110000 )!
b101000111001110000000 *!
#1305555566
1&
1<
b1 u!
b1 S!
b1 1!
#1333333344
0%
0&
0<
#1361111122
1&
1<
b10 1!
b10 S!
b10 u!
#1388888900
0&
0<
#1416666678
1%
1&
1<
b0 u!
b0 S!
b0 1!
#1444444456
b1000 :
b10001000 (
b110001 9
0&
0K
1J
0I
0<
b100101100101100000000 (!
b111100110011111100000 )!
b100101100101100000000 *!
#1472222234
1&
1<
b1 1!
b1 S!
b1 u!
#1500000012
0%
0&
0<
#1527777790
1&
1<
b10 u!
b10 S!
b10 1!
#1555555568
0&
0<
#1583333346
1%
1&
1<
b0 1!
b0 S!
b0 u!
#1611111124
b1001 :
b10111111 (
b1001111 9
0&
1M
1L
1K
1I
1H
0<
b110100110010010100000 (!
b1010101011001111000100 )!
b110100110010010100000 *!
#1638888902
1&
1<
b1 u!
b1 S!
b1 1!
#1666666680
0%
0&
0<
#1694444458
1&
1<
b10 1!
b10 S!
b10 u!
#1722222236
0&
0<
#1750000014
1%
1&
1<
b0 u!
b0 S!
b0 1!
#1777777792
b1010 :
b111000001 (
b1111011 9
0&
0L
0K
0J
0I
0H
1G
1E
0<
b1111100000101101100000 (!
b11001000110001000111100 )!
b1111100000101101100000 *!
#1805555570
1&
1<
b1 1!
b1 S!
b1 u!
#1833333348
0%
0&
0<
#1861111126
1&
1<
b10 u!
b10 S!
b10 1!
#1888888904
0&
0<
#1916666682
1%
1&
1<
b0 1!
b0 S!
b0 u!
#1944444460
b1011 :
b1001001001 (
b10111011 9
0&
1J
0F
0E
1D
0<
b10100001101011001100000 (!
b100000101100101000011100 )!
b10100001101011001100000 *!
#1972222238
1&
1<
b1 u!
b1 S!
b1 1!
#2000000016
0%
0&
0<
#2027777794
1&
1<
b10 1!
b10 S!
b10 u!
#2055555572
0&
0<
#2083333350
1%
1&
1<
b0 u!
b0 S!
b0 1!
#2111111128
b1100 :
b10000001000 (
b100100111 9
0&
0M
0G
0D
1C
0<
b100011101001101100000000 (!
b111001101011100111100000 )!
b100011101001101100000000 *!
#2138888906
1&
1<
b1 1!
b1 S!
b1 u!
#2166666684
0%
0&
0<
#2194444462
1&
1<
b10 u!
b10 S!
b10 1!
#2222222240
0&
0<
#2250000018
1%
1&
1<
b0 1!
b0 S!
b0 u!
#2277777796
b1101 :
b1001111111110 (
b1011110011 9
0&
1L
1K
1I
1H
1G
1F
1E
1D
0C
1A
0<
b10110000110011100101000000 (!
b100011110000011110110001000 )!
b10110000110011100101000000 *!
#2305555574
1&
1<
b1 u!
b1 S!
b1 1!
#2333333352
0%
0&
0<
#2361111130
1&
1<
b10 1!
b10 S!
b10 u!
#2388888908
0&
0<
#2416666686
1%
1&
1<
b0 u!
b0 S!
b0 1!
#2444444464
b1110 :
b1110001110000000 (
b100001111 9
0&
0L
0K
0J
0I
0H
0G
0A
1@
1?
1>
0<
b11111100000011111101000000000000 (!
b11111001101000001101001000000000 )!
b11111100000011111101000000000000 *!
#2472222242
1&
1<
b1 1!
b1 S!
b1 u!
#2500000020
0%
0&
0<
#2527777798
1&
1<
b10 u!
b10 S!
b10 1!
#2555555576
0&
0<
#2583333354
1%
1&
1<
b0 1!
b0 S!
b0 u!
#2611111132
b1111 :
b1111101100001011 (
b101111100 9
0&
1M
1L
1J
0F
1B
1A
0<
b11111111010100001010010100100000 (!
b11111110111001000100100110010100 )!
b11111111010100001010010100100000 *!
#2638888910
1&
1<
b1 u!
b1 S!
b1 1!
#2666666688
0%
0&
0<
#2694444466
1&
1<
b10 1!
b10 S!
b10 u!
#2722222244
0&
0<
#2750000022
1%
1&
1<
b0 u!
b0 S!
b0 1!
#2777777800
b10000 :
b1100000100010 (
b1101011 9
0&
0M
0J
1H
0E
0D
0@
0?
0>
0<
b11010101011011001011000000 (!
b101011001010011100111111000 )!
b11010101011011001011000000 *!
#2805555578
1&
1<
b1 1!
b1 S!
b1 u!
#2833333356
0%
0&
0<
#2861111134
1&
1<
b10 u!
b10 S!
b10 1!
#2888888912
0&
0<
#2916666690
1%
1&
1<
b0 1!
b0 S!
b0 u!
#2944444468
b10001 :
b10000011101100 (
b10111100001 9
0&
0L
1K
1J
1G
1F
0B
0A
1@
0<
b100100011001001110010000000 (!
b111010111000100001101010000 )!
b100100011001001110010000000 *!
#2972222246
1&
1<
b1 u!
b1 S!
b1 1!
#3000000024
0%
0&
0<
#3027777802
1&
1<
b10 1!
b10 S!
b10 u!
#3055555580
0&
0<
#3083333358
1%
1&
1<
b0 u!
b0 S!
b0 1!
#3111111136
b10010 :
b1011111011110 (
b10110011101 9
0&
1L
1I
0H
1E
1D
1C
1A
0@
0<
b11010011000100110101000000 (!
b101010101100000011000001000 )!
b11010011000100110101000000 *!
#3138888914
1&
1<
b1 1!
b1 S!
b1 u!
#3166666692
0%
0&
0<
#3194444470
1&
1<
b10 u!
b10 S!
b10 1!
#3222222248
0&
0<
#3250000026
1%
1&
1<
b0 1!
b0 S!
b0 u!
#3277777804
b10011 :
b1101110100001 (
b101111100011 9
0&
1M
0L
0K
0J
0I
1H
0G
0C
1B
0<
b11110100010101111101100000 (!
b110001011010101001010111100 )!
b11110100010101111101100000 *!
#3305555582
1&
1<
b1 u!
b1 S!
b1 1!
#3333333360
0%
0&
0<
#3361111138
1&
1<
b10 1!
b10 S!
b10 u!
#3388888916
0&
0<
#3416666694
1%
1&
1<
b0 u!
b0 S!
b0 1!
#3444444472
b10100 :
b110000000101 (
b110000011011 9
0&
1K
0H
0F
0E
0D
1C
0A
0<
b1101010010011000011100000 (!
b10101011111110111000101100 )!
b1101010010011000011100000 *!
#3472222250
1&
1<
b1 1!
b1 S!
b1 u!
#3500000028
0%
0&
0<
#3527777806
1&
1<
b10 u!
b10 S!
b10 1!
#3555555584
0&
0<
