Design/CIC/COMB.v
////////////////////////////////////////////////////////////////////////////////
// Author: Amira Atef
// Design: A comb module.
// Date: 02-11-2025
// Description: A comb stage for CIC filter
////////////////////////////////////////////////////////////////////////////////

module COMB #(parameter DATA_WIDTH = 16, N = 1) (
    input wire clk,
    input wire rst_n,
    input wire en,
    input wire signed [DATA_WIDTH-1:0] in,
    output reg signed [DATA_WIDTH-1:0] out
);

    reg signed [DATA_WIDTH-1:0] in_reg [0: N-1];

    integer i;

    always @(posedge clk or negedge rst_n) begin
        if (!rst_n) begin
            for (i = 0; i < N; i = i+1)
                in_reg[i] <= 'd0;
            out <= 'd0;
        end else if (en) begin
            in_reg[0] <= in;
            for(i = 1; i < N; i = i+1)
                in_reg[i] <= in_reg[i-1]; 
            out <= in - in_reg[N-1]; // Simple averaging differentiator
        end
    end
endmodule

Design/CIC/INTEG.v
////////////////////////////////////////////////////////////////////////////////
// Author: Amira Atef
// Design: An integrator module.
// Date: 02-11-2025
// Description: An integration stage for CIC filter
////////////////////////////////////////////////////////////////////////////////

module INTEG #(parameter DATA_WIDTH_IN = 16, DATA_WIDTH_OUT = 16) (
    input wire clk,
    input wire rst_n,
    input wire en,
    input wire signed [DATA_WIDTH_IN-1:0] in,
    output reg signed [DATA_WIDTH_OUT-1:0] out
);

    always @(posedge clk or negedge rst_n) begin
        if (!rst_n) begin
            out <= 'd0;
        end else if (en) begin
            out <= in + out; // Simple averaging integrator
        end
    end
endmodule

Design/CIC/CIC.v
////////////////////////////////////////////////////////////////////////////////
// Author: Amira Atef
// Design: Cascaded Integrator-Comb (CIC) Filter Decimator
// Date: 02-11-2025
// Description: A CIC module using an integrator-comb structure to decimate
// a signal's fs from 6MHz using an 18MHz clock. This design is for a CIC where D is the Delay, 
// Q is the order, N is the differential delay (D/R) and R is the decimation factor and R can be 1,2,4,8,16.
////////////////////////////////////////////////////////////////////////////////

module CIC #(parameter DATA_WIDTH = 16, Q = 1, N = 1) (
    input wire clk, // 18MHz, to avoid CDC
    input wire rst_n,
    input wire [4:0] R,
    input wire signed [DATA_WIDTH-1:0] x_in,
    output reg signed [DATA_WIDTH-1:0] x_out
);
    genvar i;

    reg [3:0] LOG2_D;

    always @(*) begin
        case (R)
            1: LOG2_D = 0; 
            2: LOG2_D = 1; 
            4: LOG2_D = 2; 
            8: LOG2_D = 3; 
            16: LOG2_D = 4; 
            default:  LOG2_D = 0;
        endcase
    end                   

    wire signed [(DATA_WIDTH + 6)-1:0] integrator_out [0:Q-1];
    wire signed [(DATA_WIDTH + 6)-1:0] comb_out [0:Q-1];
    reg signed [(DATA_WIDTH + 6)-1:0] downsampler_out;
    reg signed [(DATA_WIDTH + 6)-1:0] integ_buf [0:Q<<1];
    reg [7:0] sample_count;
    reg [1:0] count_og;
    reg [6:0] count_down;
    reg en_d;
    integer m, k, j;

    INTEG #(.DATA_WIDTH_IN(DATA_WIDTH), .DATA_WIDTH_OUT(DATA_WIDTH + 6)) U_INTEG_0 (.clk(clk), .rst_n(rst_n), .en(count_og[1]), .in(x_in), .out(integrator_out[0]));

    COMB #(.DATA_WIDTH(DATA_WIDTH + 6), .N(N)) U_COMB_0 (.clk(clk), .rst_n(rst_n), .en(en_d), .in(downsampler_out), .out(comb_out[0]));
    generate
        for (i = 1; i < Q; i = i + 1) begin : gen_integ_comb
            INTEG #(.DATA_WIDTH_IN(DATA_WIDTH + 6), .DATA_WIDTH_OUT(DATA_WIDTH + 6)) U_INTEG (.clk(clk), .rst_n(rst_n), .en(count_og[1]), .in(integrator_out[i-1]), .out(integrator_out[i]));
            COMB #(.DATA_WIDTH(DATA_WIDTH + 6), .N(N)) U_COMB (.clk(clk), .rst_n(rst_n), .en(en_d), .in(comb_out[i-1]), .out(comb_out[i]));
        end
    endgenerate

    always @(posedge clk or negedge rst_n) begin
        if (!rst_n) begin
            downsampler_out <= 'd0;
            sample_count <= 8'd0;
            count_og <= 2'b0;
            count_down <= 7'd0;
            en_d <= 1'b0;
            k <= 0;
            j <= 0;
            for (m = 0; m <= Q<<1; m = m + 1) begin
                integ_buf[m] <= 'd0;
            end
        end else begin
            if(count_og[1]) begin// for 6MHz
                count_og <= 2'b0;
                if(sample_count == 0) begin
                    integ_buf[k] <= integrator_out[Q-1];
                    if (k < (Q<<1))
                        k <= k + 1;
                    else
                        k <= 0;
                end
                if (sample_count < R-1) 
                    sample_count <= sample_count + 1;
                else 
                    sample_count <= 8'd0;
            end else
                count_og <= count_og + 1;
            if (en_d) begin
                en_d <= 1'b0;
                count_down <= 7'd0;
                downsampler_out <= integ_buf[j];
                if (j < (Q<<1))
                    j <= j + 1;
                else
                    j <= 0;
                // x_out <= comb_out[Q-1]>>(Q*LOG2_D); // divide by D^Q
                x_out <= (comb_out[Q-1] + (1 << (Q*LOG2_D - 1))) >> (Q*LOG2_D); // to mimic MATLAB's rounding behaviour
            end
            else begin // downsampler enable logic
                if (count_down < (3 << LOG2_D)) begin
                    if (count_down == (3 << LOG2_D)-2)
                        en_d <= 1'b1;
                    count_down <= count_down + 1;
                end 
            end
        end
    end   

    // assign x_out = comb_out[Q-1];
endmodule

Design/CIC/CIC_tb.v
`timescale 1ns/1fs
module CIC_tb();

    /////////////////////////////////////////////////////////
    ///////////////////// Parameters ////////////////////////
    /////////////////////////////////////////////////////////

    parameter CLOCK_PERIOD = 55.555556;
    parameter CLOCK_PERIOD_6 = CLOCK_PERIOD * 3;
    parameter R = 16;
    parameter CLOCK_PERIOD_R = CLOCK_PERIOD_6 *R;
    parameter DATA_WIDTH = 16;
    parameter DATA_DEPTH = 64;

    /////////////////////////////////////////////////////////
    /////////// Testbench Signal Declaration ////////////////
    /////////////////////////////////////////////////////////

    reg clk_6, clk_R;
    reg clk_tb, rst_n_tb;
    reg [4:0] R_tb;
    reg signed [DATA_WIDTH-1:0] x_in_tb; // s16.15 format
    wire signed [DATA_WIDTH-1:0] x_out_tb; // s16.15 format

    reg signed [DATA_WIDTH-1:0] mem_in [0:DATA_DEPTH-1]; // memory to store input samples

    integer i;

    ////////////////////////////////////////////////////////
    /////////////////// DUT Instantation ///////////////////
    ////////////////////////////////////////////////////////

    CIC #(.DATA_WIDTH(DATA_WIDTH)) DUT (.clk(clk_tb), .rst_n(rst_n_tb), .R(R_tb),.x_in(x_in_tb), .x_out(x_out_tb));

    ////////////////////////////////////////////////////////
    ////////////////// Clock Generator  ////////////////////
    ////////////////////////////////////////////////////////

    always #(CLOCK_PERIOD/2) clk_tb = ~clk_tb;
    always #(CLOCK_PERIOD_6/2) clk_6 = ~clk_6;
    always #(CLOCK_PERIOD_R/2) clk_R = ~clk_R;

    ////////////////////////////////////////////////////////
    /////////// Applying Stimulus on Inputs //////////////// 
    ////////////////////////////////////////////////////////

    initial begin
        // System Functions
        $dumpfile("CIC.vcd");
        $dumpvars;
        // Load input samples from file
        $readmemh("inputs_CIC.txt", mem_in);

        // initialization
        initialize();
        
        for (i = 0; i < DATA_DEPTH; i = i + 1) begin
            x_in_tb = mem_in[i];
            #(CLOCK_PERIOD_6); // for 9MHz input rate
        end

        #(500*CLOCK_PERIOD)
        $stop;
    end

    ////////////////////////////////////////////////////////
    /////////////////////// TASKS //////////////////////////
    ////////////////////////////////////////////////////////

    /////////////// Signals Initialization //////////////////

    task initialize;
        begin
            clk_tb  	  = 1'b0;
            clk_6         = 1'b0;
            clk_R         = 1'b0;
            R_tb          = R;
            // x_in_tb       = 16'sd16384; // 0.5 in s16.15 format
            reset();
        end	
    endtask

    ///////////////////////// RESET /////////////////////////

    task reset;
        begin
            rst_n_tb = 1'b1;
            #(CLOCK_PERIOD)
            rst_n_tb = 1'b0;
            #(CLOCK_PERIOD)
            rst_n_tb = 1'b1;
        end
    endtask

    ////////////////// Check Out Response  ////////////////////

endmodule

Design/CIC/CIC.vcd
$date
	Wed Nov 12 15:24:14 2025
$end
$version
	QuestaSim Version 2021.1
$end
$timescale
	1fs
$end

$scope module CIC_tb $end
$var parameter 0 ! CLOCK_PERIOD $end
$var parameter 0 " CLOCK_PERIOD_6 $end
$var parameter 32 # R $end
$var parameter 0 $ CLOCK_PERIOD_R $end
$var parameter 32 % DATA_WIDTH $end
$var parameter 32 & DATA_DEPTH $end
$var reg 1 ' clk_6 $end
$var reg 1 ( clk_R $end
$var reg 1 ) clk_tb $end
$var reg 1 * rst_n_tb $end
$var reg 5 + R_tb [4:0] $end
$var reg 16 , x_in_tb [15:0] $end
$var wire 1 - x_out_tb [15] $end
$var wire 1 . x_out_tb [14] $end
$var wire 1 / x_out_tb [13] $end
$var wire 1 0 x_out_tb [12] $end
$var wire 1 1 x_out_tb [11] $end
$var wire 1 2 x_out_tb [10] $end
$var wire 1 3 x_out_tb [9] $end
$var wire 1 4 x_out_tb [8] $end
$var wire 1 5 x_out_tb [7] $end
$var wire 1 6 x_out_tb [6] $end
$var wire 1 7 x_out_tb [5] $end
$var wire 1 8 x_out_tb [4] $end
$var wire 1 9 x_out_tb [3] $end
$var wire 1 : x_out_tb [2] $end
$var wire 1 ; x_out_tb [1] $end
$var wire 1 < x_out_tb [0] $end
$var integer 32 = i $end

$scope task initialize $end
$upscope $end

$scope task reset $end
$upscope $end

$scope module DUT $end
$var parameter 32 > DATA_WIDTH $end
$var parameter 32 ? Q $end
$var parameter 32 @ N $end
$var wire 1 A clk $end
$var wire 1 B rst_n $end
$var wire 1 C R [4] $end
$var wire 1 D R [3] $end
$var wire 1 E R [2] $end
$var wire 1 F R [1] $end
$var wire 1 G R [0] $end
$var wire 1 H x_in [15] $end
$var wire 1 I x_in [14] $end
$var wire 1 J x_in [13] $end
$var wire 1 K x_in [12] $end
$var wire 1 L x_in [11] $end
$var wire 1 M x_in [10] $end
$var wire 1 N x_in [9] $end
$var wire 1 O x_in [8] $end
$var wire 1 P x_in [7] $end
$var wire 1 Q x_in [6] $end
$var wire 1 R x_in [5] $end
$var wire 1 S x_in [4] $end
$var wire 1 T x_in [3] $end
$var wire 1 U x_in [2] $end
$var wire 1 V x_in [1] $end
$var wire 1 W x_in [0] $end
$var reg 16 X x_out [15:0] $end
$var reg 4 Y LOG2_D [3:0] $end
$var wire 1 Z integrator_out [0] $end
$var wire 1 [ integrator_out [1] $end
$var wire 1 \ integrator_out [2] $end
$var wire 1 ] integrator_out [3] $end
$var wire 1 ^ integrator_out [4] $end
$var wire 1 _ integrator_out [5] $end
$var wire 1 ` integrator_out [6] $end
$var wire 1 a integrator_out [7] $end
$var wire 1 b integrator_out [8] $end
$var wire 1 c integrator_out [9] $end
$var wire 1 d integrator_out [10] $end
$var wire 1 e integrator_out [11] $end
$var wire 1 f integrator_out [12] $end
$var wire 1 g integrator_out [13] $end
$var wire 1 h integrator_out [14] $end
$var wire 1 i integrator_out [15] $end
$var wire 1 j integrator_out [16] $end
$var wire 1 k integrator_out [17] $end
$var wire 1 l integrator_out [18] $end
$var wire 1 m integrator_out [19] $end
$var wire 1 n integrator_out [20] $end
$var wire 1 o integrator_out [21] $end
$var wire 1 p comb_out [0] $end
$var wire 1 q comb_out [1] $end
$var wire 1 r comb_out [2] $end
$var wire 1 s comb_out [3] $end
$var wire 1 t comb_out [4] $end
$var wire 1 u comb_out [5] $end
$var wire 1 v comb_out [6] $end
$var wire 1 w comb_out [7] $end
$var wire 1 x comb_out [8] $end
$var wire 1 y comb_out [9] $end
$var wire 1 z comb_out [10] $end
$var wire 1 { comb_out [11] $end
$var wire 1 | comb_out [12] $end
$var wire 1 } comb_out [13] $end
$var wire 1 ~ comb_out [14] $end
$var wire 1 !! comb_out [15] $end
$var wire 1 "! comb_out [16] $end
$var wire 1 #! comb_out [17] $end
$var wire 1 $! comb_out [18] $end
$var wire 1 %! comb_out [19] $end
$var wire 1 &! comb_out [20] $end
$var wire 1 '! comb_out [21] $end
$var reg 22 (! downsampler_out [21:0] $end
$var reg 8 )! sample_count [7:0] $end
$var reg 2 *! count_og [1:0] $end
$var reg 7 +! count_down [6:0] $end
$var reg 1 ,! en_d $end
$var integer 32 -! m $end
$var integer 32 .! k $end
$var integer 32 /! j $end

$scope module U_INTEG_0 $end
$var parameter 32 0! DATA_WIDTH_IN $end
$var parameter 32 1! DATA_WIDTH_OUT $end
$var wire 1 A clk $end
$var wire 1 B rst_n $end
$var wire 1 2! en $end
$var wire 1 H in [15] $end
$var wire 1 I in [14] $end
$var wire 1 J in [13] $end
$var wire 1 K in [12] $end
$var wire 1 L in [11] $end
$var wire 1 M in [10] $end
$var wire 1 N in [9] $end
$var wire 1 O in [8] $end
$var wire 1 P in [7] $end
$var wire 1 Q in [6] $end
$var wire 1 R in [5] $end
$var wire 1 S in [4] $end
$var wire 1 T in [3] $end
$var wire 1 U in [2] $end
$var wire 1 V in [1] $end
$var wire 1 W in [0] $end
$var reg 22 3! out [21:0] $end
$upscope $end

$scope module U_COMB_0 $end
$var parameter 32 4! DATA_WIDTH $end
$var parameter 32 5! N $end
$var wire 1 A clk $end
$var wire 1 B rst_n $end
$var wire 1 6! en $end
$var wire 1 7! in [21] $end
$var wire 1 8! in [20] $end
$var wire 1 9! in [19] $end
$var wire 1 :! in [18] $end
$var wire 1 ;! in [17] $end
$var wire 1 <! in [16] $end
$var wire 1 =! in [15] $end
$var wire 1 >! in [14] $end
$var wire 1 ?! in [13] $end
$var wire 1 @! in [12] $end
$var wire 1 A! in [11] $end
$var wire 1 B! in [10] $end
$var wire 1 C! in [9] $end
$var wire 1 D! in [8] $end
$var wire 1 E! in [7] $end
$var wire 1 F! in [6] $end
$var wire 1 G! in [5] $end
$var wire 1 H! in [4] $end
$var wire 1 I! in [3] $end
$var wire 1 J! in [2] $end
$var wire 1 K! in [1] $end
$var wire 1 L! in [0] $end
$var reg 22 M! out [21:0] $end
$var integer 32 N! i $end
$upscope $end
$upscope $end
$upscope $end
$enddefinitions $end
#0
$dumpvars
0'
0(
0)
1*
b10000 +
bx ,
bx X
b100 Y
bx (!
bx )!
bx *!
bx +!
x,!
bx 3!
bx M!
b10000 #
b10000 %
b1000000 &
b10000 >
b1 ?
b1 @
b10000 0!
b10110 1!
b10110 4!
b1 5!
r55.555556 !
r166.666668 "
r2666.666688 $
bx =
bx -!
bx .!
bx /!
bx N!
x<
x;
x:
x9
x8
x7
x6
x5
x4
x3
x2
x1
x0
x/
x.
x-
xZ
x[
x\
x]
x^
x_
x`
xa
xb
xc
xd
xe
xf
xg
xh
xi
xj
xk
xl
xm
xn
xo
xp
xq
xr
xs
xt
xu
xv
xw
xx
xy
xz
x{
x|
x}
x~
x!!
x"!
x#!
x$!
x%!
x&!
x'!
xW
xV
xU
xT
xS
xR
xQ
xP
xO
xN
xM
xL
xK
xJ
xI
xH
0G
0F
0E
0D
1C
1B
0A
xL!
xK!
xJ!
xI!
xH!
xG!
xF!
xE!
xD!
xC!
xB!
xA!
x@!
x?!
x>!
x=!
x<!
x;!
x:!
x9!
x8!
x7!
x6!
x2!
$end
#27777778
1)
1A
#55555556
0*
0)
0B
0A
b0 N!
b1 N!
b0 -!
b1 -!
b10 -!
b11 -!
b0 3!
b0 M!
b0 (!
b0 )!
b0 *!
b0 +!
0,!
b0 .!
b0 /!
02!
0L!
0K!
0J!
0I!
0H!
0G!
0F!
0E!
0D!
0C!
0B!
0A!
0@!
0?!
0>!
0=!
0<!
0;!
0:!
09!
08!
07!
0p
0q
0r
0s
0t
0u
0v
0w
0x
0y
0z
0{
0|
0}
0~
0!!
0"!
0#!
0$!
0%!
0&!
0'!
0Z
0[
0\
0]
0^
0_
0`
0a
0b
0c
0d
0e
0f
0g
0h
0i
0j
0k
0l
0m
0n
0o
06!
#83333334
1'
1)
1A
b0 N!
b1 N!
b0 -!
b1 -!
b10 -!
b11 -!
#111111112
1*
b0 =
b1000000110000100 ,
0)
0W
0V
1U
0T
0S
0R
0Q
1P
1O
0N
0M
0L
0K
0J
0I
1H
1B
0A
#138888890
1)
1A
b1 *!
b1 +!
#166666668
0'
0)
0A
#194444446
1)
1A
b10 *!
b10 +!
12!
#222222224
0)
0A
#250000002
1'
1)
1A
b1111111000000110000100 3!
b0 *!
b1 .!
b1 )!
b11 +!
02!
1\
1a
1b
1i
1j
1k
1l
1m
1n
1o
#277777780
b1 =
b110111101110111 ,
0)
1W
1V
1S
1R
1Q
0P
1N
1M
1L
1J
1I
0H
0A
#305555558
1)
1A
b1 *!
b100 +!
#333333336
0'
0)
0A
#361111114
1)
1A
b10 *!
b101 +!
12!
#388888892
0)
0A
#416666670
1'
1)
1A
b1111111111000011111011 3!
b0 *!
b10 )!
b110 +!
02!
1Z
1[
0\
1]
1^
1_
1`
0b
1f
1g
1h
#444444448
b10 =
b1000111010101111 ,
0)
1T
0S
0Q
1P
0O
0J
0I
1H
0A
#472222226
1)
1A
b1 *!
b111 +!
#500000004
0'
0)
0A
#527777782
1)
1A
b10 *!
b1000 +!
12!
#555555560
0)
0A
#583333338
1'
1)
1A
b1111110111111110101010 3!
b0 *!
b11 )!
b1001 +!
02!
0Z
0^
0`
1b
1c
1d
1e
0i
#611111116
b11 =
b1010110011010 ,
0)
0W
0U
1S
0R
1O
0N
0L
1K
0H
0A
#638888894
1)
1A
b1 *!
b1010 +!
#666666672
0'
0)
0A
#694444450
1)
1A
b10 *!
b1011 +!
12!
#722222228
0)
0A
#750000006
1'
1)
1A
b1111111001010101000100 3!
b0 *!
b100 )!
b1100 +!
02!
0[
1\
0]
0_
1`
0a
0c
0e
0g
0h
1i
#777777784
b100 =
b100000000000000 ,
0)
0V
0T
0S
0P
0O
0M
0K
1I
0A
#805555562
1)
1A
b1 *!
b1101 +!
#833333340
0'
0)
0A
#861111118
1)
1A
b10 *!
b1110 +!
12!
#888888896
0)
0A
#916666674
1'
1)
1A
b1111111101010101000100 3!
b0 *!
b101 )!
b1111 +!
02!
1h
#944444452
b101 =
b1001010101111110 ,
0)
1V
1U
1T
1S
1R
1Q
1O
1M
1K
0I
1H
0A
#972222230
1)
1A
b1 *!
b10000 +!
#1000000008
0'
0)
0A
#1027777786
1)
1A
b10 *!
b10001 +!
12!
#1055555564
0)
0A
#1083333342
1'
1)
1A
b1111110110101011000010 3!
b0 *!
b110 )!
b10010 +!
02!
1[
0\
1a
0b
1c
0d
1e
0f
1g
0i
#1111111120
b110 =
b1101101000111100 ,
0)
0V
0Q
0O
1N
0M
1L
1I
0A
#1138888898
1)
1A
b1 *!
b10011 +!
#1166666676
0'
0)
0A
#1194444454
1)
1A
b10 *!
b10100 +!
12!
#1222222232
0)
0A
#1250000010
1'
1)
1A
b1111110100010011111110 3!
b0 *!
b111 )!
b10101 +!
02!
1\
1]
1^
1_
0c
1d
0e
0g
#1277777788
b111 =
b1110111000110100 ,
0)
0T
1M
0K
1J
0A
#1305555566
1)
1A
b1 *!
b10110 +!
#1333333344
1(
0'
0)
0A
#1361111122
1)
1A
b10 *!
b10111 +!
12!
#1388888900
0)
0A
#1416666678
1'
1)
1A
b1111110011001100110010 3!
b0 *!
b1000 )!
b11000 +!
02!
0\
0]
0`
0a
1b
1c
0d
1f
1g
0h
#1444444456
b1000 =
b1101100001101 ,
0)
1W
1T
0S
0R
1O
0M
1K
0J
0I
0H
0A
#1472222234
1)
1A
b1 *!
b11001 +!
#1500000012
0'
0)
0A
#1527777790
1)
1A
b10 *!
b11010 +!
12!
#1555555568
0)
0A
#1583333346
1'
1)
1A
b1111110100111000111111 3!
b0 *!
b1001 )!
b11011 +!
02!
1Z
1\
1]
0b
1d
1e
0f
0g
1h
#1611111124
b1001 =
b1001010100011011 ,
0)
1V
0U
1S
0N
1M
0L
1H
0A
#1638888902
1)
1A
b1 *!
b11100 +!
#1666666680
0'
0)
0A
#1694444458
1)
1A
b10 *!
b11101 +!
12!
#1722222236
0)
0A
#1750000014
1'
1)
1A
b1111101110001101011010 3!
b0 *!
b1010 )!
b11110 +!
02!
0Z
0\
0_
1`
1b
0d
0e
1g
1i
0j
#1777777792
b1010 =
b1111000101111 ,
0)
1U
0S
1R
0O
1N
1L
0H
0A
#1805555570
1)
1A
b1 *!
b11111 +!
#1833333348
0'
0)
0A
#1861111126
1)
1A
b10 *!
b100000 +!
12!
#1888888904
0)
0A
#1916666682
1'
1)
1A
b1111110000000110001001 3!
b0 *!
b1011 )!
b100001 +!
02!
1Z
0[
0^
0`
1a
0c
0g
0h
0i
1j
#1944444460
b1011 =
b1011001001100000 ,
0)
0W
0V
0U
0T
1Q
0M
0L
1J
1H
0A
#1972222238
1)
1A
b1 *!
b100010 +!
#2000000016
0'
0)
0A
#2027777794
1)
1A
b10 *!
b100011 +!
12!
#2055555572
0)
0A
#2083333350
1'
1)
1A
b1111101011001111101001 3!
b0 *!
b1100 )!
b100100 +!
02!
1_
1`
1c
1f
1g
1i
0j
#2111111128
b1100 =
b10000111100 ,
0)
1U
1T
1S
0Q
0N
1M
0K
0J
0H
0A
#2138888906
1)
1A
b1 *!
b100101 +!
#2166666684
0'
0)
0A
#2194444462
1)
1A
b10 *!
b100110 +!
12!
#2222222240
0)
0A
#2250000018
1'
1)
1A
b1111101011100000100101 3!
b0 *!
b1101 )!
b100111 +!
02!
1\
0]
0`
0a
0b
0c
1e
#2277777796
b1101 =
b10100111000000 ,
0)
0U
0T
0S
0R
1Q
1P
1O
0M
1L
1J
0A
#2305555574
1)
1A
b1 *!
b101000 +!
#2333333352
0'
0)
0A
#2361111130
1)
1A
b10 *!
b101001 +!
12!
#2388888908
0)
0A
#2416666686
1'
1)
1A
b1111101110000111100101 3!
b0 *!
b1110 )!
b101010 +!
02!
1`
1a
1b
0e
0f
1h
#2444444464
b1110 =
b1010011101110 ,
0)
1V
1U
1T
1R
0O
1M
0L
1K
0J
0A
#2472222242
1)
1A
b1 *!
b101011 +!
#2500000020
0'
0)
0A
#2527777798
1)
1A
b10 *!
b101100 +!
12!
#2555555576
0)
0A
#2583333354
1'
1)
1A
b1111101111011011010011 3!
b0 *!
b1111 )!
b101101 +!
02!
1[
0\
1^
0_
0b
1c
1d
1f
#2611111132
b1111 =
b100010101001001 ,
0)
1W
0V
0U
0R
0P
1O
0K
1I
0A
#2638888910
1)
1A
b1 *!
b101110 +!
#2666666688
0(
0'
0)
0A
#2694444466
1)
1A
b10 *!
1,!
b101111 +!
12!
16!
#2722222244
0)
0A
#2750000022
1'
1)
1A
b1111110011110000011100 3!
b0 *!
b0 )!
0,!
b0 +!
b1 /!
b0 X
02!
06!
0<
0;
0:
09
08
07
06
05
04
03
02
01
00
0/
0.
0-
0Z
0[
1\
1]
0`
0a
0c
1e
0h
0i
1j
#2777777800
b10000 =
b100000001100011 ,
0)
1V
0T
1R
0O
0M
0A
#2805555578
1)
1A
b1 *!
b1 +!
#2833333356
0'
0)
0A
#2861111134
1)
1A
b10 *!
b10 +!
12!
#2888888912
0)
0A
#2916666690
1'
1)
1A
b1111110111110001111111 3!
b0 *!
b10 .!
b1 )!
b11 +!
02!
1Z
1[
1_
1`
1h
#2944444468
b10001 =
b1101011001010111 ,
0)
1U
1S
0R
1N
1M
1K
1H
0A
#2972222246
1)
1A
b1 *!
b100 +!
#3000000024
0'
0)
0A
#3027777802
1)
1A
b10 *!
b101 +!
12!
#3055555580
0)
0A
#3083333358
1'
1)
1A
b1111110101001011010110 3!
b0 *!
b10 )!
b110 +!
02!
0Z
0]
0_
1a
1c
0d
0e
0g
#3111111136
b10010 =
b1000001110011 ,
0)
0U
1R
0N
0M
0I
0H
0A
#3138888914
1)
1A
b1 *!
b111 +!
#3166666692
0'
0)
0A
#3194444470
1)
1A
b10 *!
b1000 +!
12!
#3222222248
0)
0A
#3250000026
1'
1)
1A
b1111110110001101001001 3!
b0 *!
b11 )!
b1001 +!
02!
1Z
0[
0\
1]
0^
0a
1b
0f
1g
#3277777804
b10011 =
b1100001110001111 ,
0)
1U
1T
0S
0R
0Q
1P
1O
1N
0K
1I
1H
0A
#3305555582
1)
1A
b1 *!
b1010 +!
#3333333360
0'
0)
0A
#3361111138
1)
1A
b10 *!
b1011 +!
12!
#3388888916
0)
0A
#3416666694
1'
1)
1A
b1111110010011011011000 3!
b0 *!
b100 )!
b1100 +!
02!
0Z
1^
1a
0b
1d
0h
#3444444472
b10100 =
b1010101101100111 ,
0)
0T
1R
1Q
0P
1L
1J
0I
0A
#3472222250
1)
1A
b1 *!
b1101 +!
#3500000028
0'
0)
0A
#3527777806
1)
1A
b10 *!
b1110 +!
12!
#3555555584
0)
0A
#3583333362
1'
1)
1A
b1111101101001000111111 3!
b0 *!
b101 )!
b1111 +!
02!
1Z
1[
1\
1_
0`
0a
0d
1f
0g
1h
1i
0j
#3611111140
b10101 =
b11101100110000 ,
0)
0W
0V
0U
1S
0Q
1K
0H
0A
#3638888918
1)
1A
b1 *!
b10000 +!
#3666666696
0'
0)
0A
#3694444474
1)
1A
b10 *!
b10001 +!
12!
#3722222252
0)
0A
#3750000030
1'
1)
1A
b1111110000110101101111 3!
b0 *!
b110 )!
b10010 +!
02!
0^
1`
1b
0c
1d
1e
0f
0h
0i
1j
#3777777808
b10110 =
b0 ,
0)
0S
0R
0O
0N
0L
0K
0J
0A
#3805555586
1)
1A
b1 *!
b10011 +!
#3833333364
0'
0)
0A
#3861111142
1)
1A
b10 *!
b10100 +!
12!
#3888888920
0)
0A
#3916666698
1'
1)
1A
b0 *!
b111 )!
b10101 +!
02!
#3944444476
b10111 =
b1111110001111100 ,
0)
1U
1T
1S
1R
1Q
1M
1L
1K
1J
1I
1H
0A
#3972222254
1)
1A
b1 *!
b10110 +!
#4000000032
1(
0'
0)
0A
#4027777810
1)
1A
b10 *!
b10111 +!
12!
#4055555588
0)
0A
#4083333366
1'
1)
1A
b1111110000100111101011 3!
b0 *!
b1000 )!
b11000 +!
02!
0\
1a
0d
#4111111144
b11000 =
b11101001001111 ,
0)
1W
1V
0S
0R
1N
0M
0I
0H
0A
#4138888922
1)
1A
b1 *!
b11001 +!
#4166666700
0'
0)
0A
#4194444478
1)
1A
b10 *!
b11010 +!
12!
#4222222256
0)
0A
#4250000034
1'
1)
1A
b1111110100010000111010 3!
b0 *!
b1001 )!
b11011 +!
02!
0Z
1^
0`
0a
0b
1d
0e
1h
#4277777812
b11001 =
b10011000001101 ,
0)
0V
0Q
1M
0L
0K
0A
#4305555590
1)
1A
b1 *!
b11100 +!
#4333333368
0'
0)
0A
#4361111146
1)
1A
b10 *!
b11101 +!
12!
#4388888924
0)
0A
#4416666702
1'
1)
1A
b1111110110101001000111 3!
b0 *!
b1010 )!
b11110 +!
02!
1Z
1\
0]
0^
0_
1`
1c
0d
1e
1g
#4444444480
b11010 =
b1011001101001 ,
0)
0U
1R
1Q
1K
0J
0A
#4472222258
1)
1A
b1 *!
b11111 +!
#4500000036
0'
0)
0A
#4527777814
1)
1A
b10 *!
b100000 +!
12!
#4555555592
0)
0A
#4583333370
1'
1)
1A
b1111111000000010110000 3!
b0 *!
b1011 )!
b100001 +!
02!
0Z
0[
0\
1^
1_
0`
1a
0c
0e
0g
0h
1i
#4611111148
b11011 =
b101000000000100 ,
0)
0W
1U
0T
0R
0Q
0N
0M
1I
0A
#4638888926
1)
1A
b1 *!
b100010 +!
#4666666704
0'
0)
0A
#4694444482
1)
1A
b10 *!
b100011 +!
12!
#4722222260
0)
0A
#4750000038
1'
1)
1A
b1111111101000010110100 3!
b0 *!
b1100 )!
b100100 +!
02!
1\
1f
1h
#4777777816
b11100 =
b11101110000001 ,
0)
1W
0U
1P
1O
1N
1L
1J
0I
0A
#4805555594
1)
1A
b1 *!
b100101 +!
#4833333372
0'
0)
0A
#4861111150
1)
1A
b10 *!
b100110 +!
12!
#4888888928
0)
0A
#4916666706
1'
1)
1A
b110000110101 3!
b0 *!
b1101 )!
b100111 +!
02!
1Z
0a
1d
1e
0f
0h
0i
0j
0k
0l
0m
0n
0o
#4944444484
b11101 =
b111101011000 ,
0)
0W
1T
1S
1Q
0P
1M
0K
0J
0A
#4972222262
1)
1A
b1 *!
b101000 +!
#5000000040
0'
0)
0A
#5027777818
1)
1A
b10 *!
b101001 +!
12!
#5055555596
0)
0A
#5083333374
1'
1)
1A
b1101110001101 3!
b0 *!
b1110 )!
b101010 +!
02!
1]
0^
0_
1a
1b
1c
0d
1f
#5111111152
b11110 =
b1101001111010001 ,
0)
1W
0T
1P
0M
0L
1K
1I
1H
0A
#5138888930
1)
1A
b1 *!
b101011 +!
#5166666708
0'
0)
0A
#5194444486
1)
1A
b10 *!
b101100 +!
12!
#5222222264
0)
0A
#5250000042
1'
1)
1A
b1111111110111101011110 3!
b0 *!
b1111 )!
b101101 +!
02!
0Z
1[
1^
1`
0a
1d
0f
1g
1h
1i
1j
1k
1l
1m
1n
1o
#5277777820
b11111 =
b1101011001001100 ,
0)
0W
1U
1T
0S
0P
0O
1M
0A
#5305555598
1)
1A
b1 *!
b101110 +!
#5333333376
0(
0'
0)
0A
#5361111154
1)
1A
b10 *!
1,!
b101111 +!
12!
16!
#5388888932
0)
0A
#5416666710
1'
1)
1A
b1111111100010110101010 3!
b0 *!
b0 )!
0,!
b0 +!
b1111110011110000011100 (!
b10 /!
02!
06!
1J!
1I!
1H!
1B!
1A!
1@!
1?!
1<!
1;!
1:!
19!
18!
17!
0\
0^
1_
0`
1a
0c
0e
0g
#5444444488
b100000 =
b100110001001011 ,
0)
1W
1V
0U
0N
1L
0K
0H
0A
#5472222266
1)
1A
b1 *!
b1 +!
#5500000044
0'
0)
0A
#5527777822
1)
1A
b10 *!
b10 +!
12!
#5555555600
0)
0A
#5583333378
1'
1)
1A
b1000111110101 3!
b0 *!
b0 .!
b1 )!
b11 +!
02!
1Z
0[
1\
0]
1^
1`
0d
1f
0h
0i
0j
0k
0l
0m
0n
0o
#5611111156
b100001 =
b1001100011010111 ,
0)
1U
0T
1S
1P
0M
1K
0I
1H
0A
